README.md
setup.py
src/pure_agent/__init__.py
src/pure_agent/agents.py
src/pure_agent/append_msgs.py
src/pure_agent/cache.py
src/pure_agent/client.py
src/pure_agent/common.py
src/pure_agent/tasks.py
src/pure_agent/test_client.py
src/pure_agent/tools.py
src/pure_agent/utils.py
src/pure_agent.egg-info/PKG-INFO
src/pure_agent.egg-info/SOURCES.txt
src/pure_agent.egg-info/dependency_links.txt
src/pure_agent.egg-info/top_level.txt
tests/test.py
tests/test_cache.py
tests/test_dp_agent.py
tests/test_litedict.py
tests/test_loglevel.py
tests/test_with_tools.py