Metadata-Version: 2.1
Name: pure_agent
Version: 0.1.3
Summary: A brief description of the package.
Home-page: https://github.com/yourusername/pbot
Author: Your Name
Author-email: your.email@example.com
License: MIT
Classifier: Development Status :: 3 - Alpha
Classifier: Intended Audience :: Developers
Classifier: License :: OSI Approved :: MIT License
Classifier: Programming Language :: Python :: 3
Classifier: Programming Language :: Python :: 3.6
Classifier: Programming Language :: Python :: 3.7
Classifier: Programming Language :: Python :: 3.8
Requires-Python: >=3.6
